CHANGES.txt
COPYRIGHT.txt
CREDITS.txt
LICENSE.txt
README.txt
ZopePublicLicense.txt
bootstrap.py
buildout.cfg
setup.py
src/hurry/__init__.py
src/hurry.file.egg-info/PKG-INFO
src/hurry.file.egg-info/SOURCES.txt
src/hurry.file.egg-info/dependency_links.txt
src/hurry.file.egg-info/namespace_packages.txt
src/hurry.file.egg-info/not-zip-safe
src/hurry.file.egg-info/requires.txt
src/hurry.file.egg-info/top_level.txt
src/hurry/file/README.txt
src/hurry/file/__init__.py
src/hurry/file/configure.zcml
src/hurry/file/file.py
src/hurry/file/interfaces.py
src/hurry/file/schema.py
src/hurry/file/tests.py
src/hurry/file/browser/__init__.py
src/hurry/file/browser/file.txt
src/hurry/file/browser/tests.py
src/hurry/file/browser/widget.py