Metadata-Version: 1.0
Name: hurry.file
Version: 1.2.1
Summary: hurry.file is an advanced Zope 3 file widget which tries its best to behave
